{
    "settings": {
        "_": "Settings",
        "groups": {
            "Соц.сети": {
                "📨Чат": "https://t.me/acl_chat",
                "💡Instagram": "https://instagram.com/acl.tournament",
                "🖍 TikTok": "https://www.tiktok.com/@acl_tournament",
                "📌 Steam Group": "http://steamcommunity.com/groups/firstplaygame",
                "♻Бот обратной связи": "https://t.me/ACL_feed_Bot",
                "🔵Discord🟡": "https://discord.gg/auKd4xGUb4"
            },
            "Правила": {
                "Группы": "https://telegra.ph/Pravila-povedeniya-v-chate-12-30",
                "Турнира": "https://telegra.ph/Pravila-turnira-09-21"
            },
            "Турнир": {
                "Ссылка": ""
            },
            "Реквизиты": {
                "Скины": "https://steamcommunity.com/tradeoffer/new/?partner=310787303&token=8dNiyxlC"
            }
        }
    },
    "chats": {},
    "left": {}
}